README.md
setup.py
pytransaction/__init__.py
pytransaction.egg-info/PKG-INFO
pytransaction.egg-info/SOURCES.txt
pytransaction.egg-info/dependency_links.txt
pytransaction.egg-info/top_level.txt