Metadata-Version: 2.1
Name: pytransaction
Version: 1.0.0
Summary: run revert functions when exception occurs in context
Home-page: https://github.com/thuhak/pytransaction.git
Author: thuhak
Author-email: thuhak.zhou@nio.com
License: UNKNOWN
Keywords: transaction
Platform: UNKNOWN
